aybIG/__init__.py
aybIG/api.py
aybIG-0.1.2.dist-info/METADATA
aybIG-0.1.2.dist-info/WHEEL
aybIG-0.1.2.dist-info/top_level.txt
aybIG-0.1.2.dist-info/RECORD
