Metadata-Version: 2.1
Name: aybIG
Version: 0.1.2
Summary: Instagram API logic for user data extraction
Home-page: UNKNOWN
Author: AYOUB QADDA
License: UNKNOWN
Platform: UNKNOWN
Classifier: Programming Language :: Python :: 3
Classifier: License :: OSI Approved :: MIT License
Classifier: Operating System :: OS Independent
Requires-Python: >=3.6
